aind_data_schema_models/__init__.py
aind_data_schema_models/atlas.py
aind_data_schema_models/brain_atlas.py
aind_data_schema_models/coordinates.py
aind_data_schema_models/data_name_patterns.py
aind_data_schema_models/devices.py
aind_data_schema_models/gene.py
aind_data_schema_models/harp_types.py
aind_data_schema_models/licenses.py
aind_data_schema_models/modalities.py
aind_data_schema_models/mouse_anatomy.py
aind_data_schema_models/organizations.py
aind_data_schema_models/pid_names.py
aind_data_schema_models/process_names.py
aind_data_schema_models/protocols.py
aind_data_schema_models/reagent.py
aind_data_schema_models/registries.py
aind_data_schema_models/slap2_acquisition_type.py
aind_data_schema_models/species.py
aind_data_schema_models/specimen_procedure_types.py
aind_data_schema_models/stimulus_modality.py
aind_data_schema_models/system_architecture.py
aind_data_schema_models/units.py
aind_data_schema_models/utils.py
aind_data_schema_models/_generators/__init__.py
aind_data_schema_models/_generators/dev_utils.py
aind_data_schema_models/_generators/generator.py
aind_data_schema_models/_generators/update_harp_types.py
aind_data_schema_models/_generators/models/atlas.csv
aind_data_schema_models/_generators/models/brain_atlas.csv
aind_data_schema_models/_generators/models/harp_types.csv
aind_data_schema_models/_generators/models/modalities.csv
aind_data_schema_models/_generators/models/mouse_anatomy.csv
aind_data_schema_models/_generators/models/organizations.csv
aind_data_schema_models/_generators/models/process_names.csv
aind_data_schema_models/_generators/models/protocols.csv
aind_data_schema_models/_generators/models/registries.csv
aind_data_schema_models/_generators/models/slap2_acquisition_type.csv
aind_data_schema_models/_generators/models/species.csv
aind_data_schema_models/_generators/models/specimen_procedure_types.csv
aind_data_schema_models/_generators/models/stimulus_modality.csv
aind_data_schema_models/_generators/templates/atlas.txt
aind_data_schema_models-5.2.3.dist-info/licenses/LICENSE
aind_data_schema_models-5.2.3.dist-info/METADATA
aind_data_schema_models-5.2.3.dist-info/WHEEL
aind_data_schema_models-5.2.3.dist-info/top_level.txt
aind_data_schema_models-5.2.3.dist-info/RECORD
