Metadata-Version: 2.4
Name: aind-data-schema-models
Version: 5.2.3
Summary: Generated from aind-library-template
Author: Allen Institute for Neural Dynamics
License: MIT
Classifier: Programming Language :: Python :: 3
Requires-Python: >=3.10
License-File: LICENSE
Requires-Dist: pydantic>=2.7
Requires-Dist: importlib-resources
Requires-Dist: requests
Provides-Extra: dev
Requires-Dist: codespell; extra == "dev"
Requires-Dist: black>=25.0.0; extra == "dev"
Requires-Dist: coverage; extra == "dev"
Requires-Dist: flake8; extra == "dev"
Requires-Dist: interrogate; extra == "dev"
Requires-Dist: isort; extra == "dev"
Requires-Dist: Sphinx; extra == "dev"
Requires-Dist: furo; extra == "dev"
Requires-Dist: aind-flake8-extensions==0.5.2; extra == "dev"
Requires-Dist: jinja2; extra == "dev"
Requires-Dist: pandas; extra == "dev"
Requires-Dist: pyyaml; extra == "dev"
Provides-Extra: build
Requires-Dist: aind-data-access-api<2.0,>=1.9.2; extra == "build"
Dynamic: license-file
